eternity/__init__.py
eternity/eternity.py
RTRASmall-0.1.0.dist-info/LICENSE
RTRASmall-0.1.0.dist-info/METADATA
RTRASmall-0.1.0.dist-info/WHEEL
RTRASmall-0.1.0.dist-info/top_level.txt
RTRASmall-0.1.0.dist-info/RECORD
