Metadata-Version: 2.1
Name: RTRASmall
Version: 0.1.0
Summary: Python library for real-time data retrieval from the web
Home-page: https://github.com/yourusername/eternity
Author: udit Raj
Author-email: udit_2312res708@iitp.ac.in
License: MIT
Classifier: Programming Language :: Python :: 3
Classifier: License :: OSI Approved :: MIT License
Classifier: Operating System :: OS Independent
License-File: LICENSE
Requires-Dist: requests
